LICENSE
MANIFEST.in
README.md
requirements.txt
setup.cfg
setup.py
chatflow/__init__.py
chatflow/chatflow.py
chatflow.egg-info/PKG-INFO
chatflow.egg-info/SOURCES.txt
chatflow.egg-info/dependency_links.txt
chatflow.egg-info/not-zip-safe
chatflow.egg-info/requires.txt
chatflow.egg-info/top_level.txt