Metadata-Version: 1.1
Name: chatflow
Version: 0.0.1a0
Summary: Python Package for ChatBot Developer
Home-page: https://github.com/lesimor/chatflow_pkg
Author: ByungWook Kang
Author-email: lesimor@naver.com
License: MIT
Keywords: chatflow,chatbot
Platform: UNKNOWN
Classifier: Programming Language :: Python :: 3
Classifier: Programming Language :: Python :: 3.2
Classifier: Programming Language :: Python :: 3.3
Classifier: Programming Language :: Python :: 3.4
Classifier: Programming Language :: Python :: 3.5
Classifier: Programming Language :: Python :: 3.6
